odoo/addons/hr_timesheet_sheet_policy_project_manager/README.rst
odoo/addons/hr_timesheet_sheet_policy_project_manager/__init__.py
odoo/addons/hr_timesheet_sheet_policy_project_manager/__manifest__.py
odoo/addons/hr_timesheet_sheet_policy_project_manager/i18n/es.po
odoo/addons/hr_timesheet_sheet_policy_project_manager/i18n/hr_timesheet_sheet_policy_project_manager.pot
odoo/addons/hr_timesheet_sheet_policy_project_manager/i18n/it.po
odoo/addons/hr_timesheet_sheet_policy_project_manager/i18n/pt_BR.po
odoo/addons/hr_timesheet_sheet_policy_project_manager/models/__init__.py
odoo/addons/hr_timesheet_sheet_policy_project_manager/models/account_analytic_line.py
odoo/addons/hr_timesheet_sheet_policy_project_manager/models/hr_timesheet_sheet.py
odoo/addons/hr_timesheet_sheet_policy_project_manager/models/res_company.py
odoo/addons/hr_timesheet_sheet_policy_project_manager/readme/CONFIGURE.md
odoo/addons/hr_timesheet_sheet_policy_project_manager/readme/CONTRIBUTORS.md
odoo/addons/hr_timesheet_sheet_policy_project_manager/readme/DESCRIPTION.md
odoo/addons/hr_timesheet_sheet_policy_project_manager/readme/USAGE.md
odoo/addons/hr_timesheet_sheet_policy_project_manager/static/description/icon.png
odoo/addons/hr_timesheet_sheet_policy_project_manager/static/description/index.html
odoo/addons/hr_timesheet_sheet_policy_project_manager/tests/__init__.py
odoo/addons/hr_timesheet_sheet_policy_project_manager/tests/test_hr_timesheet_sheet_policy_project_manager.py
odoo/addons/hr_timesheet_sheet_policy_project_manager/views/hr_timesheet_sheet.xml
odoo_addon_hr_timesheet_sheet_policy_project_manager-18.0.1.0.0.2.dist-info/METADATA
odoo_addon_hr_timesheet_sheet_policy_project_manager-18.0.1.0.0.2.dist-info/WHEEL
odoo_addon_hr_timesheet_sheet_policy_project_manager-18.0.1.0.0.2.dist-info/top_level.txt
odoo_addon_hr_timesheet_sheet_policy_project_manager-18.0.1.0.0.2.dist-info/RECORD
